{"nodes": [{"id": "c_users_acer_documents_projects_docmind_app_src_app_page_tsx", "label": "page.tsx", "file_type": "code", "source_file": "C:\\Users\\acer\\Documents\\projects\\Docmind-app\\src\\app\\page.tsx", "source_location": "L1"}, {"id": "app_page_handledocopen", "label": "handleDocOpen()", "file_type": "code", "source_file": "C:\\Users\\acer\\Documents\\projects\\Docmind-app\\src\\app\\page.tsx", "source_location": "L48"}], "edges": [{"source": "c_users_acer_documents_projects_docmind_app_src_app_page_tsx", "target": "react", "relation": "imports_from", "context": "import", "confidence": "EXTRACTED", "source_file": "C:\\Users\\acer\\Documents\\projects\\Docmind-app\\src\\app\\page.tsx", "source_location": "L3", "weight": 1.0}, {"source": "c_users_acer_documents_projects_docmind_app_src_app_page_tsx", "target": "c_users_acer_documents_projects_docmind_app_src_hooks_useappstate", "relation": "imports_from", "context": "import", "confidence": "EXTRACTED", "source_file": "C:\\Users\\acer\\Documents\\projects\\Docmind-app\\src\\app\\page.tsx", "source_location": "L4", "weight": 1.0}, {"source": "c_users_acer_documents_projects_docmind_app_src_app_page_tsx", "target": "hooks_useappstate_useappstate", "relation": "imports", "context": "import", "confidence": "EXTRACTED", "source_file": "C:\\Users\\acer\\Documents\\projects\\Docmind-app\\src\\app\\page.tsx", "source_location": "L4", "weight": 1.0}, {"source": "c_users_acer_documents_projects_docmind_app_src_app_page_tsx", "target": "c_users_acer_documents_projects_docmind_app_src_hooks_usedocuments", "relation": "imports_from", "context": "import", "confidence": "EXTRACTED", "source_file": "C:\\Users\\acer\\Documents\\projects\\Docmind-app\\src\\app\\page.tsx", "source_location": "L5", "weight": 1.0}, {"source": "c_users_acer_documents_projects_docmind_app_src_app_page_tsx", "target": "hooks_usedocuments_usedocuments", "relation": "imports", "context": "import", "confidence": "EXTRACTED", "source_file": "C:\\Users\\acer\\Documents\\projects\\Docmind-app\\src\\app\\page.tsx", "source_location": "L5", "weight": 1.0}, {"source": "c_users_acer_documents_projects_docmind_app_src_app_page_tsx", "target": "c_users_acer_documents_projects_docmind_app_src_components_layout_sidebar", "relation": "imports_from", "context": "import", "confidence": "EXTRACTED", "source_file": "C:\\Users\\acer\\Documents\\projects\\Docmind-app\\src\\app\\page.tsx", "source_location": "L6", "weight": 1.0}, {"source": "c_users_acer_documents_projects_docmind_app_src_app_page_tsx", "target": "layout_sidebar_sidebar", "relation": "imports", "context": "import", "confidence": "EXTRACTED", "source_file": "C:\\Users\\acer\\Documents\\projects\\Docmind-app\\src\\app\\page.tsx", "source_location": "L6", "weight": 1.0}, {"source": "c_users_acer_documents_projects_docmind_app_src_app_page_tsx", "target": "c_users_acer_documents_projects_docmind_app_src_components_dashboard_dashboard", "relation": "imports_from", "context": "import", "confidence": "EXTRACTED", "source_file": "C:\\Users\\acer\\Documents\\projects\\Docmind-app\\src\\app\\page.tsx", "source_location": "L7", "weight": 1.0}, {"source": "c_users_acer_documents_projects_docmind_app_src_app_page_tsx", "target": "dashboard_dashboard_dashboard", "relation": "imports", "context": "import", "confidence": "EXTRACTED", "source_file": "C:\\Users\\acer\\Documents\\projects\\Docmind-app\\src\\app\\page.tsx", "source_location": "L7", "weight": 1.0}, {"source": "c_users_acer_documents_projects_docmind_app_src_app_page_tsx", "target": "c_users_acer_documents_projects_docmind_app_src_components_workspace_workspace", "relation": "imports_from", "context": "import", "confidence": "EXTRACTED", "source_file": "C:\\Users\\acer\\Documents\\projects\\Docmind-app\\src\\app\\page.tsx", "source_location": "L8", "weight": 1.0}, {"source": "c_users_acer_documents_projects_docmind_app_src_app_page_tsx", "target": "workspace_workspace_workspace", "relation": "imports", "context": "import", "confidence": "EXTRACTED", "source_file": "C:\\Users\\acer\\Documents\\projects\\Docmind-app\\src\\app\\page.tsx", "source_location": "L8", "weight": 1.0}, {"source": "c_users_acer_documents_projects_docmind_app_src_app_page_tsx", "target": "c_users_acer_documents_projects_docmind_app_src_components_onboarding_modeselect", "relation": "imports_from", "context": "import", "confidence": "EXTRACTED", "source_file": "C:\\Users\\acer\\Documents\\projects\\Docmind-app\\src\\app\\page.tsx", "source_location": "L9", "weight": 1.0}, {"source": "c_users_acer_documents_projects_docmind_app_src_app_page_tsx", "target": "onboarding_modeselect_modeselect", "relation": "imports", "context": "import", "confidence": "EXTRACTED", "source_file": "C:\\Users\\acer\\Documents\\projects\\Docmind-app\\src\\app\\page.tsx", "source_location": "L9", "weight": 1.0}, {"source": "c_users_acer_documents_projects_docmind_app_src_app_page_tsx", "target": "c_users_acer_documents_projects_docmind_app_src_lib_modes", "relation": "imports_from", "context": "import", "confidence": "EXTRACTED", "source_file": "C:\\Users\\acer\\Documents\\projects\\Docmind-app\\src\\app\\page.tsx", "source_location": "L10", "weight": 1.0}, {"source": "c_users_acer_documents_projects_docmind_app_src_app_page_tsx", "target": "lib_modes_mode", "relation": "imports", "context": "import", "confidence": "EXTRACTED", "source_file": "C:\\Users\\acer\\Documents\\projects\\Docmind-app\\src\\app\\page.tsx", "source_location": "L10", "weight": 1.0}, {"source": "c_users_acer_documents_projects_docmind_app_src_app_page_tsx", "target": "app_page_handledocopen", "relation": "contains", "confidence": "EXTRACTED", "source_file": "C:\\Users\\acer\\Documents\\projects\\Docmind-app\\src\\app\\page.tsx", "source_location": "L48", "weight": 1.0}], "raw_calls": [{"caller_nid": "app_page_handledocopen", "callee": "setActiveDocId", "is_member_call": false, "source_file": "C:\\Users\\acer\\Documents\\projects\\Docmind-app\\src\\app\\page.tsx", "source_location": "L49"}, {"caller_nid": "app_page_handledocopen", "callee": "setView", "is_member_call": false, "source_file": "C:\\Users\\acer\\Documents\\projects\\Docmind-app\\src\\app\\page.tsx", "source_location": "L50"}]}